[
  {
    "id": "de413d13-227e-454e-879a-d3392dfe1c1e",
    "name": "[美国] CloudFlare - CDN节点 - 052fdd.823",
    "type": "vmess",
    "server": "104.21.82.183",
    "port": 8880,
    "clash_config": {
      "name": "[美国] CloudFlare - CDN节点 - 052fdd.823",
      "type": "vmess",
      "server": "104.21.82.183",
      "port": 8880,
      "uuid": "5a7021e0-26b4-45d6-b175-fe551601ca97",
      "alterId": 0,
      "cipher": "auto",
      "udp": true,
      "tls": false,
      "skip-cert-verify": true,
      "network": "ws",
      "ws-path": "/",
      "ws-headers": {
        "Host": "server26.beheshtbaneh.com"
      }
    },
    "source": "https://raw.githubusercontent.com/freefq/free/master/v2",
    "latency": 8,
    "last_checked": "2025-06-24T13:46:09.205057+00:00"
  },
  {
    "id": "9792291c-fcc1-46a5-a4fe-4f592d470175",
    "name": "[美国] CloudFlare - 节点 - 42ae10.1910",
    "type": "vmess",
    "server": "SSxXZASw.999824.Xyz",
    "port": 80,
    "clash_config": {
      "name": "[美国] CloudFlare - 节点 - 42ae10.1910",
      "type": "vmess",
      "server": "SSxXZASw.999824.Xyz",
      "port": 80,
      "uuid": "512d9674-db12-44ca-a1b5-654244549b65",
      "alterId": 0,
      "cipher": "auto",
      "udp": true,
      "tls": false,
      "skip-cert-verify": true,
      "network": "ws",
      "ws-path": "/uiAxvH6OkVk0VCfa7dX3JIrYk7zm",
      "ws-headers": {
        "Host": "ssxxzasw.999824.xyz"
      }
    },
    "source": "https://raw.githubusercontent.com/Pawdroid/Free-servers/main/sub",
    "latency": 6,
    "last_checked": "2025-06-24T13:46:09.205192+00:00"
  },
  {
    "id": "427c864f-5ac0-4eef-88f5-9e9663ef93ee",
    "name": "[美国] CloudFlare - 节点 - 694c1d.1910",
    "type": "vmess",
    "server": "EeEDCFVg.999824.xYZ",
    "port": 80,
    "clash_config": {
      "name": "[美国] CloudFlare - 节点 - 694c1d.1910",
      "type": "vmess",
      "server": "EeEDCFVg.999824.xYZ",
      "port": 80,
      "uuid": "cdec9d57-661d-456a-bbf2-b4c38e9c6711",
      "alterId": 0,
      "cipher": "auto",
      "udp": true,
      "tls": false,
      "skip-cert-verify": true,
      "network": "ws",
      "ws-path": "/9dZlJLjHHrL0VwSolbqFpg",
      "ws-headers": {
        "Host": "eeedcfvg.999824.xyz"
      }
    },
    "source": "https://raw.githubusercontent.com/Pawdroid/Free-servers/main/sub",
    "latency": 5,
    "last_checked": "2025-06-24T13:46:09.205261+00:00"
  },
  {
    "id": "298abfce-681b-45bf-b416-b3d4be9552a7",
    "name": "[美国] CloudFlare - 节点 - 1a6d4d.107",
    "type": "vmess",
    "server": "xxxcvfbghy7.222767.xyz",
    "port": "80",
    "clash_config": {
      "name": "[美国] CloudFlare - 节点 - 1a6d4d.107",
      "type": "vmess",
      "server": "xxxcvfbghy7.222767.xyz",
      "port": 80,
      "uuid": "30602b6d-5d5c-4f56-9b65-9ae2fd9348cb",
      "alterId": 0,
      "cipher": "auto",
      "udp": true,
      "tls": false,
      "skip-cert-verify": true,
      "network": "ws",
      "ws-path": "/TetDjP6oSiF3sGVHqPd73hl",
      "ws-headers": {
        "Host": "xxxcvfbghy7.222767.xyz"
      }
    },
    "source": "https://raw.githubusercontent.com/Pawdroid/Free-servers/main/sub",
    "latency": 5,
    "last_checked": "2025-06-24T13:46:09.205351+00:00"
  },
  {
    "id": "ed720805-6b19-41b4-9314-36dc9c0fc16e",
    "name": "[美国] Fastly - Anycast节点 - 98a9ff.1284",
    "type": "vmess",
    "server": "gov.uk",
    "port": 443,
    "clash_config": {
      "name": "[美国] Fastly - Anycast节点 - 98a9ff.1284",
      "type": "vmess",
      "server": "gov.uk",
      "port": 443,
      "uuid": "77848824-93b7-4b89-ffd0-e91afff406ce",
      "alterId": 0,
      "cipher": "auto",
      "udp": true,
      "tls": true,
      "skip-cert-verify": true,
      "network": "ws",
      "ws-path": "/77848824",
      "ws-headers": {
        "Host": "zheshiscp.com"
      }
    },
    "source": "https://raw.githubusercontent.com/freefq/free/master/v2",
    "latency": 13,
    "last_checked": "2025-06-24T13:46:09.253470+00:00"
  },
  {
    "id": "15d09a2d-2c14-418f-abdf-fa81e8142146",
    "name": "[美国] CloudFlare - 节点 - ea50ed.1910",
    "type": "vmess",
    "server": "eERRRty6.999824.xyz",
    "port": 443,
    "clash_config": {
      "name": "[美国] CloudFlare - 节点 - ea50ed.1910",
      "type": "vmess",
      "server": "eERRRty6.999824.xyz",
      "port": 443,
      "uuid": "512d9674-db12-44ca-a1b5-654244549b65",
      "alterId": 0,
      "cipher": "auto",
      "udp": true,
      "tls": true,
      "skip-cert-verify": true,
      "network": "ws",
      "ws-path": "/uiAxvH6OkVk0VCfa7dX3JIrYk7zm",
      "ws-headers": {
        "Host": "eerrrty6.999824.xyz"
      }
    },
    "source": "https://raw.githubusercontent.com/Pawdroid/Free-servers/main/sub",
    "latency": 20,
    "last_checked": "2025-06-24T13:46:09.278194+00:00"
  },
  {
    "id": "32206d32-dede-414b-b585-cf393c6694e9",
    "name": "[美国] 未知服务商 - 节点 - 11d5b1.39",
    "type": "trojan",
    "server": "104.21.3.189",
    "port": 443,
    "clash_config": {
      "name": "[美国] 未知服务商 - 节点 - 11d5b1.39",
      "type": "trojan",
      "server": "104.21.3.189",
      "port": 443,
      "password": "509ed9b7-8d64-4204-8ec8-6b749020ac3f",
      "udp": true,
      "skip-cert-verify": true
    },
    "source": "https://raw.githubusercontent.com/aiboboxx/v2rayfree/main/v2",
    "latency": 5,
    "last_checked": "2025-06-24T13:46:09.370360+00:00"
  },
  {
    "id": "7c8c9de6-5dd1-4325-980f-6e8cb3d64912",
    "name": "[韩国] 未知服务商 - 节点 - b63cd6.1364",
    "type": "vmess",
    "server": "45.141.136.234",
    "port": 49815,
    "clash_config": {
      "name": "[韩国] 未知服务商 - 节点 - b63cd6.1364",
      "type": "vmess",
      "server": "45.141.136.234",
      "port": 49815,
      "uuid": "105af49c-e4ee-4294-b7cc-abfe6a651cf5",
      "alterId": 0,
      "cipher": "auto",
      "udp": true,
      "tls": false,
      "skip-cert-verify": true
    },
    "source": "https://raw.githubusercontent.com/aiboboxx/v2rayfree/main/v2",
    "latency": 182,
    "last_checked": "2025-06-24T13:46:09.380339+00:00"
  },
  {
    "id": "048dcb69-e855-40d6-bdb2-33d9c3ce3c29",
    "name": "[美国] 未知服务商 - 节点 - 592303.233",
    "type": "vmess",
    "server": "85.198.23.63",
    "port": "52262",
    "clash_config": {
      "name": "[美国] 未知服务商 - 节点 - 592303.233",
      "type": "vmess",
      "server": "85.198.23.63",
      "port": 52262,
      "uuid": "af5a0d0c-c898-4a51-ba6a-47179d483e41",
      "alterId": 0,
      "cipher": "auto",
      "udp": true,
      "tls": false,
      "skip-cert-verify": true
    },
    "source": "https://raw.githubusercontent.com/ermaozi/get_subscribe/main/subscribe/v2ray.txt",
    "latency": 200,
    "last_checked": "2025-06-24T13:46:09.391046+00:00"
  },
  {
    "id": "04f51d0f-60b5-4323-8eea-747a49421e57",
    "name": "[韩国] 未知服务商 - 节点 - e639df.1364",
    "type": "vmess",
    "server": "45.141.136.234",
    "port": "49815",
    "clash_config": {
      "name": "[韩国] 未知服务商 - 节点 - e639df.1364",
      "type": "vmess",
      "server": "45.141.136.234",
      "port": 49815,
      "uuid": "105af49c-e4ee-4294-b7cc-abfe6a651cf5",
      "alterId": 0,
      "cipher": "auto",
      "udp": true,
      "tls": false,
      "skip-cert-verify": true
    },
    "source": "https://raw.githubusercontent.com/aiboboxx/v2rayfree/main/v2",
    "latency": 192,
    "last_checked": "2025-06-24T13:46:09.471866+00:00"
  },
  {
    "id": "0c0a7506-bb46-4b21-9e9c-201529f02dfa",
    "name": "[韩国] 未知服务商 - 节点 - 051582.1364",
    "type": "vmess",
    "server": "45.141.136.234",
    "port": 49815,
    "clash_config": {
      "name": "[韩国] 未知服务商 - 节点 - 051582.1364",
      "type": "vmess",
      "server": "45.141.136.234",
      "port": 49815,
      "uuid": "105af49c-e4ee-4294-b7cc-abfe6a651cf5",
      "alterId": 0,
      "cipher": "auto",
      "udp": true,
      "tls": false,
      "skip-cert-verify": true
    },
    "source": "https://raw.githubusercontent.com/aiboboxx/v2rayfree/main/v2",
    "latency": 206,
    "last_checked": "2025-06-24T13:46:09.647736+00:00"
  },
  {
    "id": "ebb4d40f-8eba-42f3-b9a9-66848d1604d5",
    "name": "[日本] 未知服务商 - 节点 - 494740.1364",
    "type": "ss",
    "server": "103.163.218.2",
    "port": 989,
    "clash_config": {
      "name": "[日本] 未知服务商 - 节点 - 494740.1364",
      "type": "ss",
      "server": "103.163.218.2",
      "port": 989,
      "cipher": "aes-256-gcm",
      "password": "",
      "udp": true
    },
    "source": "https://raw.githubusercontent.com/aiboboxx/v2rayfree/main/v2",
    "latency": 339,
    "last_checked": "2025-06-24T13:46:09.700171+00:00"
  },
  {
    "id": "91ebd691-7112-41e6-9a07-160c2159d109",
    "name": "[韩国] 未知服务商 - 节点 - 3e885a.1364",
    "type": "vmess",
    "server": "45.141.136.234",
    "port": "49815",
    "clash_config": {
      "name": "[韩国] 未知服务商 - 节点 - 3e885a.1364",
      "type": "vmess",
      "server": "45.141.136.234",
      "port": 49815,
      "uuid": "105af49c-e4ee-4294-b7cc-abfe6a651cf5",
      "alterId": 0,
      "cipher": "auto",
      "udp": true,
      "tls": false,
      "skip-cert-verify": true
    },
    "source": "https://raw.githubusercontent.com/aiboboxx/v2rayfree/main/v2",
    "latency": 180,
    "last_checked": "2025-06-24T13:46:10.315259+00:00"
  },
  {
    "id": "777bfe99-2d4e-4af5-b1ea-7510157b3cd4",
    "name": "[香港] 未知服务商 - 节点 - c35278.1350",
    "type": "vmess",
    "server": "43.247.135.170",
    "port": 46210,
    "clash_config": {
      "name": "[香港] 未知服务商 - 节点 - c35278.1350",
      "type": "vmess",
      "server": "43.247.135.170",
      "port": 46210,
      "uuid": "d1eca706-1aae-42d3-bab0-69995d7b023d",
      "alterId": 0,
      "cipher": "auto",
      "udp": true,
      "tls": false,
      "skip-cert-verify": true
    },
    "source": "https://raw.githubusercontent.com/aiboboxx/v2rayfree/main/v2",
    "latency": 1425,
    "last_checked": "2025-06-24T13:46:10.619268+00:00"
  },
  {
    "id": "b93bce83-ec3e-46bb-8f40-5aff27c72567",
    "name": "[香港] 未知服务商 - 节点 - be045f.1350",
    "type": "vmess",
    "server": "43.247.135.170",
    "port": "46210",
    "clash_config": {
      "name": "[香港] 未知服务商 - 节点 - be045f.1350",
      "type": "vmess",
      "server": "43.247.135.170",
      "port": 46210,
      "uuid": "d1eca706-1aae-42d3-bab0-69995d7b023d",
      "alterId": 0,
      "cipher": "auto",
      "udp": true,
      "tls": false,
      "skip-cert-verify": true
    },
    "source": "https://raw.githubusercontent.com/aiboboxx/v2rayfree/main/v2",
    "latency": 1419,
    "last_checked": "2025-06-24T13:46:10.623138+00:00"
  },
  {
    "id": "ec6ec639-f1b5-4976-ab49-7dc01a720dfe",
    "name": "[美国] 未知服务商 - 节点 - f1f9f1.39",
    "type": "trojan",
    "server": "104.21.3.189",
    "port": 443,
    "clash_config": {
      "name": "[美国] 未知服务商 - 节点 - f1f9f1.39",
      "type": "trojan",
      "server": "104.21.3.189",
      "port": 443,
      "password": "509ed9b7-8d64-4204-8ec8-6b749020ac3f",
      "udp": true,
      "skip-cert-verify": true
    },
    "source": "https://raw.githubusercontent.com/aiboboxx/v2rayfree/main/v2",
    "latency": 5,
    "last_checked": "2025-06-24T13:46:10.627336+00:00"
  },
  {
    "id": "bb332f21-c530-49c6-a87d-26740c0b982a",
    "name": "[日本] 未知服务商 - 节点 - 3ffe94.1364",
    "type": "ss",
    "server": "103.163.218.2",
    "port": 989,
    "clash_config": {
      "name": "[日本] 未知服务商 - 节点 - 3ffe94.1364",
      "type": "ss",
      "server": "103.163.218.2",
      "port": 989,
      "cipher": "aes-256-gcm",
      "password": "",
      "udp": true
    },
    "source": "https://raw.githubusercontent.com/aiboboxx/v2rayfree/main/v2",
    "latency": 309,
    "last_checked": "2025-06-24T13:46:10.627440+00:00"
  },
  {
    "id": "a885a0ab-5772-465f-87b9-34ac8a4043de",
    "name": "[美国] CloudFlare - CDN节点 - 417226.823",
    "type": "vmess",
    "server": "104.21.82.183",
    "port": 8880,
    "clash_config": {
      "name": "[美国] CloudFlare - CDN节点 - 417226.823",
      "type": "vmess",
      "server": "104.21.82.183",
      "port": 8880,
      "uuid": "5a7021e0-26b4-45d6-b175-fe551601ca97",
      "alterId": 0,
      "cipher": "auto",
      "udp": true,
      "tls": false,
      "skip-cert-verify": true,
      "network": "ws",
      "ws-path": "/",
      "ws-headers": {
        "Host": "server26.beheshtbaneh.com"
      }
    },
    "source": "https://raw.githubusercontent.com/freefq/free/master/v2",
    "latency": 5,
    "last_checked": "2025-06-24T13:46:10.695669+00:00"
  },
  {
    "id": "e7e047a9-ea46-4e28-bf7b-7890078e56cb",
    "name": "[美国] Fastly - Anycast节点 - 668a9a.1924",
    "type": "vmess",
    "server": "gov.uk",
    "port": 443,
    "clash_config": {
      "name": "[美国] Fastly - Anycast节点 - 668a9a.1924",
      "type": "vmess",
      "server": "gov.uk",
      "port": 443,
      "uuid": "77848824-93b7-4b89-ffd0-e91afff406ce",
      "alterId": 0,
      "cipher": "auto",
      "udp": true,
      "tls": true,
      "skip-cert-verify": true,
      "network": "ws",
      "ws-path": "/77848824",
      "ws-headers": {
        "Host": "zheshiscp.com"
      }
    },
    "source": "https://raw.githubusercontent.com/freefq/free/master/v2",
    "latency": 12,
    "last_checked": "2025-06-24T13:46:10.819197+00:00"
  },
  {
    "id": "c9c75060-cf46-4c56-b7fd-5baf77e2e93d",
    "name": "[日本] 未知服务商 - 节点 - 438b82.961",
    "type": "vmess",
    "server": "superstar.jp1.srayx.xyz",
    "port": "80",
    "clash_config": {
      "name": "[日本] 未知服务商 - 节点 - 438b82.961",
      "type": "vmess",
      "server": "superstar.jp1.srayx.xyz",
      "port": 80,
      "uuid": "27c4d8dc-9676-4ac4-95bf-46a0e338f82e",
      "alterId": 0,
      "cipher": "auto",
      "udp": true,
      "tls": false,
      "skip-cert-verify": true,
      "network": "ws",
      "ws-path": "/superstar",
      "ws-headers": {
        "Host": "pull.free.video.10010.com"
      }
    },
    "source": "https://raw.githubusercontent.com/adiwzx/freenode/main/adispeed.txt",
    "latency": 5,
    "last_checked": "2025-06-24T13:46:10.823011+00:00"
  },
  {
    "id": "4369d730-d11a-4efa-b983-08f410bc9e65",
    "name": "[香港] 未知服务商 - 节点 - 18cee8.1350",
    "type": "vmess",
    "server": "43.247.135.170",
    "port": 46210,
    "clash_config": {
      "name": "[香港] 未知服务商 - 节点 - 18cee8.1350",
      "type": "vmess",
      "server": "43.247.135.170",
      "port": 46210,
      "uuid": "d1eca706-1aae-42d3-bab0-69995d7b023d",
      "alterId": 0,
      "cipher": "auto",
      "udp": true,
      "tls": false,
      "skip-cert-verify": true
    },
    "source": "https://raw.githubusercontent.com/aiboboxx/v2rayfree/main/v2",
    "latency": 1460,
    "last_checked": "2025-06-24T13:46:10.838867+00:00"
  },
  {
    "id": "8818e6a2-18fa-4339-bc8d-47606620ef49",
    "name": "[美国] 未知服务商 - 节点 - 702e68.125",
    "type": "vmess",
    "server": "workers.dev",
    "port": "443",
    "clash_config": {
      "name": "[美国] 未知服务商 - 节点 - 702e68.125",
      "type": "vmess",
      "server": "workers.dev",
      "port": 443,
      "uuid": "7a70e0f7-170d-4ab0-82a0-c40554bfb320",
      "alterId": 0,
      "cipher": "auto",
      "udp": true,
      "tls": true,
      "skip-cert-verify": true,
      "network": "ws",
      "ws-path": "/111111.online",
      "ws-headers": {
        "Host": "buyvm.proxypool.ga"
      }
    },
    "source": "https://raw.githubusercontent.com/adiwzx/freenode/main/adispeed.txt",
    "latency": 16,
    "last_checked": "2025-06-24T13:46:10.884442+00:00"
  },
  {
    "id": "298ce883-89c3-43e6-bf97-360dea3b445d",
    "name": "[美国] 未知服务商 - 节点 - eb5a05.1748",
    "type": "vmess",
    "server": "www.digitalocean.com",
    "port": "443",
    "clash_config": {
      "name": "[美国] 未知服务商 - 节点 - eb5a05.1748",
      "type": "vmess",
      "server": "www.digitalocean.com",
      "port": 443,
      "uuid": "3a3e263d-223f-49cc-bbdb-f7e07a55e6fe",
      "alterId": 0,
      "cipher": "auto",
      "udp": true,
      "tls": true,
      "skip-cert-verify": true,
      "network": "ws",
      "ws-path": "/111111.online",
      "ws-headers": {
        "Host": "by.6111.online"
      }
    },
    "source": "https://raw.githubusercontent.com/adiwzx/freenode/main/adispeed.txt",
    "latency": 20,
    "last_checked": "2025-06-24T13:46:10.890624+00:00"
  },
  {
    "id": "98dc8b9d-7d9f-4b92-8f06-82c996325369",
    "name": "[香港] 未知服务商 - 节点 - 4efd51.1350",
    "type": "vmess",
    "server": "43.247.135.170",
    "port": "46210",
    "clash_config": {
      "name": "[香港] 未知服务商 - 节点 - 4efd51.1350",
      "type": "vmess",
      "server": "43.247.135.170",
      "port": 46210,
      "uuid": "d1eca706-1aae-42d3-bab0-69995d7b023d",
      "alterId": 0,
      "cipher": "auto",
      "udp": true,
      "tls": false,
      "skip-cert-verify": true
    },
    "source": "https://raw.githubusercontent.com/aiboboxx/v2rayfree/main/v2",
    "latency": 1567,
    "last_checked": "2025-06-24T13:46:11.039453+00:00"
  },
  {
    "id": "cffa8ffe-ee4b-4099-b81e-3d3e86abc3de",
    "name": "[美国] 未知服务商 - 节点 - 3803ab.722",
    "type": "vmess",
    "server": "ping.pe",
    "port": "443",
    "clash_config": {
      "name": "[美国] 未知服务商 - 节点 - 3803ab.722",
      "type": "vmess",
      "server": "ping.pe",
      "port": 443,
      "uuid": "3a3e263d-223f-49cc-bbdb-f7e07a55e6fe",
      "alterId": 0,
      "cipher": "auto",
      "udp": true,
      "tls": true,
      "skip-cert-verify": true,
      "network": "ws",
      "ws-path": "/111111.online",
      "ws-headers": {
        "Host": "by.6111.online"
      }
    },
    "source": "https://raw.githubusercontent.com/adiwzx/freenode/main/adispeed.txt",
    "latency": 23,
    "last_checked": "2025-06-24T13:46:11.126883+00:00"
  },
  {
    "id": "88c2bbef-c9cf-4358-ae66-c0baef917647",
    "name": "[韩国] 未知服务商 - 节点 - 717409.1364",
    "type": "vmess",
    "server": "45.141.136.234",
    "port": "49815",
    "clash_config": {
      "name": "[韩国] 未知服务商 - 节点 - 717409.1364",
      "type": "vmess",
      "server": "45.141.136.234",
      "port": 49815,
      "uuid": "105af49c-e4ee-4294-b7cc-abfe6a651cf5",
      "alterId": 0,
      "cipher": "auto",
      "udp": true,
      "tls": false,
      "skip-cert-verify": true
    },
    "source": "https://raw.githubusercontent.com/ripaojiedian/freenode/main/sub",
    "latency": 186,
    "last_checked": "2025-06-24T13:46:12.416493+00:00"
  },
  {
    "id": "d217860c-942d-4915-b82e-39bf266e7cd9",
    "name": "[韩国] 未知服务商 - 节点 - 918229.1364",
    "type": "vmess",
    "server": "45.141.136.234",
    "port": 49815,
    "clash_config": {
      "name": "[韩国] 未知服务商 - 节点 - 918229.1364",
      "type": "vmess",
      "server": "45.141.136.234",
      "port": 49815,
      "uuid": "105af49c-e4ee-4294-b7cc-abfe6a651cf5",
      "alterId": 0,
      "cipher": "auto",
      "udp": true,
      "tls": false,
      "skip-cert-verify": true
    },
    "source": "https://raw.githubusercontent.com/peasoft/NoMoreWalls/master/list.txt",
    "latency": 182,
    "last_checked": "2025-06-24T13:46:12.645031+00:00"
  },
  {
    "id": "43ac9af5-638b-4c60-b550-358fc239c888",
    "name": "[香港] 未知服务商 - 节点 - 63fe37.1350",
    "type": "vmess",
    "server": "43.247.135.170",
    "port": "46210",
    "clash_config": {
      "name": "[香港] 未知服务商 - 节点 - 63fe37.1350",
      "type": "vmess",
      "server": "43.247.135.170",
      "port": 46210,
      "uuid": "d1eca706-1aae-42d3-bab0-69995d7b023d",
      "alterId": 0,
      "cipher": "auto",
      "udp": true,
      "tls": false,
      "skip-cert-verify": true
    },
    "source": "https://raw.githubusercontent.com/ripaojiedian/freenode/main/sub",
    "latency": 1484,
    "last_checked": "2025-06-24T13:46:13.680247+00:00"
  },
  {
    "id": "5a220476-5cd8-43d8-a1fa-6bf9c47443c6",
    "name": "[香港] 未知服务商 - 节点 - 622407.1350",
    "type": "vmess",
    "server": "43.247.135.170",
    "port": 46210,
    "clash_config": {
      "name": "[香港] 未知服务商 - 节点 - 622407.1350",
      "type": "vmess",
      "server": "43.247.135.170",
      "port": 46210,
      "uuid": "d1eca706-1aae-42d3-bab0-69995d7b023d",
      "alterId": 0,
      "cipher": "auto",
      "udp": true,
      "tls": false,
      "skip-cert-verify": true
    },
    "source": "https://raw.githubusercontent.com/peasoft/NoMoreWalls/master/list.txt",
    "latency": 1508,
    "last_checked": "2025-06-24T13:46:13.917550+00:00"
  },
  {
    "id": "004751e1-50b3-427f-ad60-cf9183de9666",
    "name": "[美国] 未知服务商 - 节点 - ae396e.39",
    "type": "trojan",
    "server": "104.21.3.189",
    "port": 443,
    "clash_config": {
      "name": "[美国] 未知服务商 - 节点 - ae396e.39",
      "type": "trojan",
      "server": "104.21.3.189",
      "port": 443,
      "password": "509ed9b7-8d64-4204-8ec8-6b749020ac3f",
      "udp": true,
      "skip-cert-verify": true
    },
    "source": "https://raw.githubusercontent.com/peasoft/NoMoreWalls/master/list.txt",
    "latency": 5,
    "last_checked": "2025-06-24T13:46:14.093435+00:00"
  },
  {
    "id": "742c60d5-df19-4bc6-92b5-f7a0cdc252f8",
    "name": "[韩国] 未知服务商 - 节点 - 152aca.1364",
    "type": "vmess",
    "server": "45.141.136.234",
    "port": "49815",
    "clash_config": {
      "name": "[韩国] 未知服务商 - 节点 - 152aca.1364",
      "type": "vmess",
      "server": "45.141.136.234",
      "port": 49815,
      "uuid": "105af49c-e4ee-4294-b7cc-abfe6a651cf5",
      "alterId": 0,
      "cipher": "auto",
      "udp": true,
      "tls": false,
      "skip-cert-verify": true
    },
    "source": "https://raw.githubusercontent.com/peasoft/NoMoreWalls/master/list.txt",
    "latency": 200,
    "last_checked": "2025-06-24T13:46:14.164960+00:00"
  },
  {
    "id": "ebae3808-20ad-4c61-b0f1-e3f2af527164",
    "name": "[新加坡] 未知服务商 - 节点 - 87bc5c.2040",
    "type": "trojan",
    "server": "103.160.204.40",
    "port": 8443,
    "clash_config": {
      "name": "[新加坡] 未知服务商 - 节点 - 87bc5c.2040",
      "type": "trojan",
      "server": "103.160.204.40",
      "port": 8443,
      "password": "d6b8011a-c725-435a-9fec-bf6d3530392c",
      "udp": true,
      "skip-cert-verify": true
    },
    "source": "https://raw.githubusercontent.com/ssrsub/ssr/master/V2Ray",
    "latency": 5,
    "last_checked": "2025-06-24T13:46:14.246325+00:00"
  },
  {
    "id": "c313f001-6703-4b41-9356-c34c45a23de1",
    "name": "[日本] 未知服务商 - 节点 - f0f403.1364",
    "type": "ss",
    "server": "103.163.218.2",
    "port": 989,
    "clash_config": {
      "name": "[日本] 未知服务商 - 节点 - f0f403.1364",
      "type": "ss",
      "server": "103.163.218.2",
      "port": 989,
      "cipher": "aes-256-gcm",
      "password": "",
      "udp": true
    },
    "source": "https://raw.githubusercontent.com/peasoft/NoMoreWalls/master/list.txt",
    "latency": 243,
    "last_checked": "2025-06-24T13:46:14.271964+00:00"
  },
  {
    "id": "66d685ff-c78f-4d26-8938-52e8297951b8",
    "name": "[美国] 未知服务商 - 节点 - d5159e.1914",
    "type": "trojan",
    "server": "172.67.191.174",
    "port": 443,
    "clash_config": {
      "name": "[美国] 未知服务商 - 节点 - d5159e.1914",
      "type": "trojan",
      "server": "172.67.191.174",
      "port": 443,
      "password": "2e65577e-8fdb-4bb1-a495-96f3122099a7",
      "udp": true,
      "skip-cert-verify": true
    },
    "source": "https://raw.githubusercontent.com/ssrsub/ssr/master/V2Ray",
    "latency": 5,
    "last_checked": "2025-06-24T13:46:14.301604+00:00"
  },
  {
    "id": "2b0293c7-1290-4fdc-a1fa-bcce1f78f1c9",
    "name": "[美国] 未知服务商 - 节点 - 992c78.161",
    "type": "trojan",
    "server": "104.21.16.1",
    "port": 443,
    "clash_config": {
      "name": "[美国] 未知服务商 - 节点 - 992c78.161",
      "type": "trojan",
      "server": "104.21.16.1",
      "port": 443,
      "password": "288124da-0d68-42f4-9f48-70dc4dcc55a6",
      "udp": true,
      "skip-cert-verify": true
    },
    "source": "https://raw.githubusercontent.com/ssrsub/ssr/master/V2Ray",
    "latency": 5,
    "last_checked": "2025-06-24T13:46:14.307201+00:00"
  },
  {
    "id": "e164a582-f79b-4833-b750-00dd59307b11",
    "name": "[香港] 未知服务商 - 节点 - c975c5.1350",
    "type": "vmess",
    "server": "43.247.135.170",
    "port": "46210",
    "clash_config": {
      "name": "[香港] 未知服务商 - 节点 - c975c5.1350",
      "type": "vmess",
      "server": "43.247.135.170",
      "port": 46210,
      "uuid": "d1eca706-1aae-42d3-bab0-69995d7b023d",
      "alterId": 0,
      "cipher": "auto",
      "udp": true,
      "tls": false,
      "skip-cert-verify": true
    },
    "source": "https://raw.githubusercontent.com/peasoft/NoMoreWalls/master/list.txt",
    "latency": 1663,
    "last_checked": "2025-06-24T13:46:14.308777+00:00"
  },
  {
    "id": "4193eea2-023a-4821-85c6-1406b4233199",
    "name": "[美国] 未知服务商 - 节点 - a8b11c.842",
    "type": "trojan",
    "server": "104.21.84.242",
    "port": 443,
    "clash_config": {
      "name": "[美国] 未知服务商 - 节点 - a8b11c.842",
      "type": "trojan",
      "server": "104.21.84.242",
      "port": 443,
      "password": "03e92910-34b1-4245-ac63-04a865f43cd5",
      "udp": true,
      "skip-cert-verify": true
    },
    "source": "https://raw.githubusercontent.com/ssrsub/ssr/master/V2Ray",
    "latency": 5,
    "last_checked": "2025-06-24T13:46:14.312469+00:00"
  },
  {
    "id": "a41efb2c-900a-4bd0-a884-043e0eb7f0af",
    "name": "[美国] 未知服务商 - 节点 - 2f1fe2.267",
    "type": "trojan",
    "server": "104.21.26.17",
    "port": 443,
    "clash_config": {
      "name": "[美国] 未知服务商 - 节点 - 2f1fe2.267",
      "type": "trojan",
      "server": "104.21.26.17",
      "port": 443,
      "password": "07a3df8f-2a2c-42f8-ad92-65889d90f3bf",
      "udp": true,
      "skip-cert-verify": true
    },
    "source": "https://raw.githubusercontent.com/ssrsub/ssr/master/V2Ray",
    "latency": 5,
    "last_checked": "2025-06-24T13:46:14.314051+00:00"
  },
  {
    "id": "d70d0ce1-fd15-4cfd-be43-0bc1feb9bc16",
    "name": "[美国] 未知服务商 - 节点 - dab1a1.1281",
    "type": "trojan",
    "server": "104.17.128.1",
    "port": 2096,
    "clash_config": {
      "name": "[美国] 未知服务商 - 节点 - dab1a1.1281",
      "type": "trojan",
      "server": "104.17.128.1",
      "port": 2096,
      "password": "d6b8011a-c725-435a-9fec-bf6d3530392c",
      "udp": true,
      "skip-cert-verify": true
    },
    "source": "https://raw.githubusercontent.com/ssrsub/ssr/master/V2Ray",
    "latency": 5,
    "last_checked": "2025-06-24T13:46:14.319782+00:00"
  },
  {
    "id": "ff652761-6c7b-4b19-8239-495c9c3cdfee",
    "name": "[美国] 未知服务商 - 节点 - eeae1c.444",
    "type": "trojan",
    "server": "172.66.44.214",
    "port": 2053,
    "clash_config": {
      "name": "[美国] 未知服务商 - 节点 - eeae1c.444",
      "type": "trojan",
      "server": "172.66.44.214",
      "port": 2053,
      "password": "T@_WvT8Ho@LW%w_,",
      "udp": true,
      "skip-cert-verify": true
    },
    "source": "https://raw.githubusercontent.com/ssrsub/ssr/master/V2Ray",
    "latency": 5,
    "last_checked": "2025-06-24T13:46:14.325288+00:00"
  },
  {
    "id": "cf419e45-6ffd-49c1-be38-1eb181e52685",
    "name": "[美国] 未知服务商 - 节点 - 7c1047.1357",
    "type": "trojan",
    "server": "172.67.135.37",
    "port": 443,
    "clash_config": {
      "name": "[美国] 未知服务商 - 节点 - 7c1047.1357",
      "type": "trojan",
      "server": "172.67.135.37",
      "port": 443,
      "password": "07a3df8f-2a2c-42f8-ad92-65889d90f3bf",
      "udp": true,
      "skip-cert-verify": true
    },
    "source": "https://raw.githubusercontent.com/ssrsub/ssr/master/V2Ray",
    "latency": 5,
    "last_checked": "2025-06-24T13:46:14.330847+00:00"
  },
  {
    "id": "a74f14f2-f952-4bfa-abc7-20150b368b3b",
    "name": "[美国] 未知服务商 - 节点 - 67f37c.1502",
    "type": "trojan",
    "server": "172.67.150.132",
    "port": 443,
    "clash_config": {
      "name": "[美国] 未知服务商 - 节点 - 67f37c.1502",
      "type": "trojan",
      "server": "172.67.150.132",
      "port": 443,
      "password": "0f7070cd-c91d-4532-a51f-56da4f0e94be",
      "udp": true,
      "skip-cert-verify": true
    },
    "source": "https://raw.githubusercontent.com/ssrsub/ssr/master/V2Ray",
    "latency": 5,
    "last_checked": "2025-06-24T13:46:14.336373+00:00"
  },
  {
    "id": "cb83cb13-c75f-4d26-985e-6413ad87a100",
    "name": "[美国] 未知服务商 - 节点 - c43144.651",
    "type": "vmess",
    "server": "XSssDcVFgt.444652.XyZ",
    "port": "443",
    "clash_config": {
      "name": "[美国] 未知服务商 - 节点 - c43144.651",
      "type": "vmess",
      "server": "XSssDcVFgt.444652.XyZ",
      "port": 443,
      "uuid": "512d9674-db12-44ca-a1b5-654244549b65",
      "alterId": 0,
      "cipher": "auto",
      "udp": true,
      "tls": true,
      "skip-cert-verify": true,
      "network": "ws",
      "ws-path": "/uiAxvH6OkVk0VCfa7dX3JIrYk7zm",
      "ws-headers": {
        "Host": "xsssdcvfgt.444652.xyz"
      }
    },
    "source": "https://raw.githubusercontent.com/ssrsub/ssr/master/V2Ray",
    "latency": 14,
    "last_checked": "2025-06-24T13:46:14.350590+00:00"
  },
  {
    "id": "089ee6f2-e55e-4fbc-b70f-d6653c82e6b1",
    "name": "[美国] 未知服务商 - 节点 - 1dbbd3.1761",
    "type": "vmess",
    "server": "104.17.176.171",
    "port": "8080",
    "clash_config": {
      "name": "[美国] 未知服务商 - 节点 - 1dbbd3.1761",
      "type": "vmess",
      "server": "104.17.176.171",
      "port": 8080,
      "uuid": "6cbc9c78-1cb1-57d4-a999-e2f4e34c1e03",
      "alterId": 0,
      "cipher": "auto",
      "udp": true,
      "tls": false,
      "skip-cert-verify": true,
      "network": "ws",
      "ws-path": "/nasnet/cdn",
      "ws-headers": {
        "Host": "ke7hz36ewz-4515017473.mashallahbet.com"
      }
    },
    "source": "https://raw.githubusercontent.com/ssrsub/ssr/master/V2Ray",
    "latency": 5,
    "last_checked": "2025-06-24T13:46:14.356609+00:00"
  },
  {
    "id": "35375541-12e0-4f5f-bdb5-b28b16c0222e",
    "name": "[美国] 未知服务商 - 节点 - 39da40.2011",
    "type": "vmess",
    "server": "45.147.201.231",
    "port": "20065",
    "clash_config": {
      "name": "[美国] 未知服务商 - 节点 - 39da40.2011",
      "type": "vmess",
      "server": "45.147.201.231",
      "port": 20065,
      "uuid": "be1456d6-4f70-447c-b49a-23ded34fe943",
      "alterId": 0,
      "cipher": "auto",
      "udp": true,
      "tls": false,
      "skip-cert-verify": true,
      "network": "ws",
      "ws-path": "/",
      "ws-headers": {
        "Host": ""
      }
    },
    "source": "https://raw.githubusercontent.com/ssrsub/ssr/master/V2Ray",
    "latency": 131,
    "last_checked": "2025-06-24T13:46:14.378580+00:00"
  },
  {
    "id": "e33babf9-0630-4b14-b598-09bd3f05df09",
    "name": "[美国] 未知服务商 - 节点 - bbd96c.1581",
    "type": "vmess",
    "server": "www.xinjuc.com",
    "port": "80",
    "clash_config": {
      "name": "[美国] 未知服务商 - 节点 - bbd96c.1581",
      "type": "vmess",
      "server": "www.xinjuc.com",
      "port": 80,
      "uuid": "2f38f848-a899-4c87-9807-207a41615e3c",
      "alterId": 0,
      "cipher": "auto",
      "udp": true,
      "tls": false,
      "skip-cert-verify": true,
      "network": "ws",
      "ws-path": "/rongseven?ed=2048",
      "ws-headers": {
        "Host": "hk.freeyyds.dpdns.org"
      }
    },
    "source": "https://raw.githubusercontent.com/ssrsub/ssr/master/V2Ray",
    "latency": 5,
    "last_checked": "2025-06-24T13:46:14.384405+00:00"
  },
  {
    "id": "ee62d52c-5aa5-4b26-8a99-5f2a69a0873a",
    "name": "[美国] 未知服务商 - 节点 - fc562c.1910",
    "type": "vmess",
    "server": "eERRRty6.999824.xyz",
    "port": "443",
    "clash_config": {
      "name": "[美国] 未知服务商 - 节点 - fc562c.1910",
      "type": "vmess",
      "server": "eERRRty6.999824.xyz",
      "port": 443,
      "uuid": "512d9674-db12-44ca-a1b5-654244549b65",
      "alterId": 0,
      "cipher": "auto",
      "udp": true,
      "tls": true,
      "skip-cert-verify": true,
      "network": "ws",
      "ws-path": "/uiAxvH6OkVk0VCfa7dX3JIrYk7zm",
      "ws-headers": {
        "Host": "eerrrty6.999824.xyz"
      }
    },
    "source": "https://raw.githubusercontent.com/ssrsub/ssr/master/V2Ray",
    "latency": 17,
    "last_checked": "2025-06-24T13:46:14.396085+00:00"
  },
  {
    "id": "536b2d6d-1f18-4ffd-920b-6ff0fcc63575",
    "name": "[美国] 未知服务商 - 节点 - bcb7cf.2544",
    "type": "trojan",
    "server": "104.25.254.4",
    "port": 2087,
    "clash_config": {
      "name": "[美国] 未知服务商 - 节点 - bcb7cf.2544",
      "type": "trojan",
      "server": "104.25.254.4",
      "port": 2087,
      "password": "d6b8011a-c725-435a-9fec-bf6d3530392c",
      "udp": true,
      "skip-cert-verify": true
    },
    "source": "https://raw.githubusercontent.com/ssrsub/ssr/master/V2Ray",
    "latency": 5,
    "last_checked": "2025-06-24T13:46:14.419464+00:00"
  },
  {
    "id": "3448f975-23e7-4654-874f-1d03147cfca7",
    "name": "[美国] 未知服务商 - 节点 - 1ec193.107",
    "type": "vmess",
    "server": "xxxcvfbghy7.222767.xyz",
    "port": "80",
    "clash_config": {
      "name": "[美国] 未知服务商 - 节点 - 1ec193.107",
      "type": "vmess",
      "server": "xxxcvfbghy7.222767.xyz",
      "port": 80,
      "uuid": "30602b6d-5d5c-4f56-9b65-9ae2fd9348cb",
      "alterId": 0,
      "cipher": "auto",
      "udp": true,
      "tls": false,
      "skip-cert-verify": true,
      "network": "ws",
      "ws-path": "/TetDjP6oSiF3sGVHqPd73hl",
      "ws-headers": {
        "Host": "xxxcvfbghy7.222767.xyz"
      }
    },
    "source": "https://raw.githubusercontent.com/ssrsub/ssr/master/V2Ray",
    "latency": 5,
    "last_checked": "2025-06-24T13:46:14.425075+00:00"
  },
  {
    "id": "073f06e2-e0ba-4e9a-b708-93ac280368dc",
    "name": "[美国] 未知服务商 - 节点 - 90a931.801",
    "type": "vmess",
    "server": "pppppPpPPl.999864.xyz",
    "port": "443",
    "clash_config": {
      "name": "[美国] 未知服务商 - 节点 - 90a931.801",
      "type": "vmess",
      "server": "pppppPpPPl.999864.xyz",
      "port": 443,
      "uuid": "69678f53-fe48-4d6f-8da1-61f90a6a1ed7",
      "alterId": 0,
      "cipher": "auto",
      "udp": true,
      "tls": true,
      "skip-cert-verify": true,
      "network": "ws",
      "ws-path": "/yZ6ou0sUqPR6MznS",
      "ws-headers": {
        "Host": "pppppppppl.999864.xyz"
      }
    },
    "source": "https://raw.githubusercontent.com/ssrsub/ssr/master/V2Ray",
    "latency": 17,
    "last_checked": "2025-06-24T13:46:14.435416+00:00"
  },
  {
    "id": "c22b3921-eb2c-44b9-8b95-fe484664e531",
    "name": "[美国] 未知服务商 - 节点 - 89ac17.460",
    "type": "trojan",
    "server": "eer.freevpnatm.dpdns.org",
    "port": 443,
    "clash_config": {
      "name": "[美国] 未知服务商 - 节点 - 89ac17.460",
      "type": "trojan",
      "server": "eer.freevpnatm.dpdns.org",
      "port": 443,
      "password": "ffcf7ec1-3e09-4821-b3d9-b426a107b73b",
      "udp": true,
      "skip-cert-verify": true
    },
    "source": "https://raw.githubusercontent.com/ssrsub/ssr/master/V2Ray",
    "latency": 5,
    "last_checked": "2025-06-24T13:46:14.441265+00:00"
  },
  {
    "id": "651c33e6-6efc-4f13-b2f2-dee16ede7ee3",
    "name": "[日本] 未知服务商 - 节点 - 8a5f67.2011",
    "type": "ss",
    "server": "77.246.102.112",
    "port": 60117,
    "clash_config": {
      "name": "[日本] 未知服务商 - 节点 - 8a5f67.2011",
      "type": "ss",
      "server": "77.246.102.112",
      "port": 60117,
      "cipher": "aes-256-gcm",
      "password": "",
      "udp": true
    },
    "source": "https://raw.githubusercontent.com/ssrsub/ssr/master/V2Ray",
    "latency": 90,
    "last_checked": "2025-06-24T13:46:15.289159+00:00"
  },
  {
    "id": "92514e7a-6bd3-4db3-a0aa-77bd39996d6a",
    "name": "[俄罗斯] 未知服务商 - 节点 - 05ed84.2011",
    "type": "vmess",
    "server": "45.147.201.231",
    "port": "22069",
    "clash_config": {
      "name": "[俄罗斯] 未知服务商 - 节点 - 05ed84.2011",
      "type": "vmess",
      "server": "45.147.201.231",
      "port": 22069,
      "uuid": "57159348-4d98-4311-a990-e62f8c70fd43",
      "alterId": 0,
      "cipher": "auto",
      "udp": true,
      "tls": false,
      "skip-cert-verify": true,
      "network": "ws",
      "ws-path": "/",
      "ws-headers": {
        "Host": ""
      }
    },
    "source": "https://raw.githubusercontent.com/ssrsub/ssr/master/V2Ray",
    "latency": 130,
    "last_checked": "2025-06-24T13:46:15.325984+00:00"
  },
  {
    "id": "c397a36b-5249-4f99-9a72-5b51d2886274",
    "name": "[香港] 未知服务商 - 节点 - 6fa0a3.1382",
    "type": "trojan",
    "server": "jp007.421421.xyz",
    "port": 20230,
    "clash_config": {
      "name": "[香港] 未知服务商 - 节点 - 6fa0a3.1382",
      "type": "trojan",
      "server": "jp007.421421.xyz",
      "port": 20230,
      "password": "fdd1d613-f234-40f6-b63d-97517e0fc4b3",
      "udp": true,
      "skip-cert-verify": true
    },
    "source": "https://raw.githubusercontent.com/ssrsub/ssr/master/V2Ray",
    "latency": 165,
    "last_checked": "2025-06-24T13:46:15.370806+00:00"
  },
  {
    "id": "5f932146-345b-4112-b4b0-da316ca7c9d9",
    "name": "[香港] 未知服务商 - 节点 - 1b713e.1124",
    "type": "vmess",
    "server": "c6008c16-sydb40-tgzvop-hns7.hk.p5pv.com",
    "port": "80",
    "clash_config": {
      "name": "[香港] 未知服务商 - 节点 - 1b713e.1124",
      "type": "vmess",
      "server": "c6008c16-sydb40-tgzvop-hns7.hk.p5pv.com",
      "port": 80,
      "uuid": "6857f1bc-f27b-11ea-87ad-f23c913c8d2b",
      "alterId": 2,
      "cipher": "auto",
      "udp": true,
      "tls": false,
      "skip-cert-verify": true,
      "network": "ws",
      "ws-path": "/",
      "ws-headers": {
        "Host": "broadcastlv.chat.bilibili.com"
      }
    },
    "source": "https://raw.githubusercontent.com/ssrsub/ssr/master/V2Ray",
    "latency": 245,
    "last_checked": "2025-06-24T13:46:15.535145+00:00"
  },
  {
    "id": "a92cd91d-1852-4ab3-acd8-e64321d8da81",
    "name": "[香港] 未知服务商 - 节点 - d6306b.1350",
    "type": "vmess",
    "server": "43.247.135.170",
    "port": "46210",
    "clash_config": {
      "name": "[香港] 未知服务商 - 节点 - d6306b.1350",
      "type": "vmess",
      "server": "43.247.135.170",
      "port": 46210,
      "uuid": "d1eca706-1aae-42d3-bab0-69995d7b023d",
      "alterId": 0,
      "cipher": "auto",
      "udp": true,
      "tls": false,
      "skip-cert-verify": true
    },
    "source": "https://raw.githubusercontent.com/ssrsub/ssr/master/V2Ray",
    "latency": 1309,
    "last_checked": "2025-06-24T13:46:16.687887+00:00"
  }
]